presalytics/__init__.py
presalytics/__main__.py
presalytics/cli.py
presalytics/client/__init__.py
presalytics/client/api.py
presalytics/client/auth.py
presalytics/client/oidc.py
presalytics/client/websocket.py
presalytics/client/doc_converter/__init__.py
presalytics/client/doc_converter/api_client.py
presalytics/client/doc_converter/configuration.py
presalytics/client/doc_converter/exceptions.py
presalytics/client/doc_converter/rest.py
presalytics/client/doc_converter/api/__init__.py
presalytics/client/doc_converter/api/default_api.py
presalytics/client/doc_converter/models/__init__.py
presalytics/client/doc_converter/models/file_to_convert.py
presalytics/client/doc_converter/models/file_url.py
presalytics/client/events/__init__.py
presalytics/client/events/api_client.py
presalytics/client/events/configuration.py
presalytics/client/events/exceptions.py
presalytics/client/events/rest.py
presalytics/client/events/api/__init__.py
presalytics/client/events/api/event_typess_api.py
presalytics/client/events/api/events_api.py
presalytics/client/events/models/__init__.py
presalytics/client/events/models/inbound_event_dto.py
presalytics/client/events/models/metadata.py
presalytics/client/events/models/related_resources.py
presalytics/client/ooxml_automation/__init__.py
presalytics/client/ooxml_automation/api_client.py
presalytics/client/ooxml_automation/configuration.py
presalytics/client/ooxml_automation/exceptions.py
presalytics/client/ooxml_automation/rest.py
presalytics/client/ooxml_automation/api/__init__.py
presalytics/client/ooxml_automation/api/default_api.py
presalytics/client/ooxml_automation/models/__init__.py
presalytics/client/ooxml_automation/models/chart_axes.py
presalytics/client/ooxml_automation/models/chart_axes_details.py
presalytics/client/ooxml_automation/models/chart_axis_data_types.py
presalytics/client/ooxml_automation/models/chart_chart_data.py
presalytics/client/ooxml_automation/models/chart_chart_data_details.py
presalytics-0.6.5.dist-info/LICENSE
presalytics-0.6.5.dist-info/METADATA
presalytics-0.6.5.dist-info/WHEEL
presalytics-0.6.5.dist-info/entry_points.txt
presalytics-0.6.5.dist-info/top_level.txt
presalytics-0.6.5.dist-info/RECORD
