Metadata-Version: 2.1
Name: presalytics
Version: 0.6.5
Summary: Presalytics Python Client
Home-page: https://presalytics.io/docs
Author-email: inquiries@presalytics.io
License: UNKNOWN
Keywords: Presalytics
Platform: UNKNOWN
License-File: LICENSE
